btcvol/__init__.py
btcvol/examples.py
btcvol/testing.py
btcvol/tracker.py
btcvol-1.2.0.dist-info/licenses/LICENSE
btcvol-1.2.0.dist-info/METADATA
btcvol-1.2.0.dist-info/WHEEL
btcvol-1.2.0.dist-info/top_level.txt
btcvol-1.2.0.dist-info/RECORD
