Metadata-Version: 2.4
Name: btcvol
Version: 1.2.0
Summary: Bitcoin Implied Volatility Prediction Competition - Participant Package
Author-email: Jeremy Berros <jberrospellenc@gmail.com>
License-Expression: MIT
Project-URL: Homepage, https://github.com/jberros/btcvol-python
Project-URL: Documentation, https://github.com/jberros/btcvol-python#readme
Project-URL: Repository, https://github.com/jberros/btcvol-python
Project-URL: Issues, https://github.com/jberros/btcvol-python/issues
Project-URL: Competition, https://www.crunchdao.com/
Keywords: bitcoin,volatility,prediction,competition,machine-learning,crunchdao
Classifier: Development Status :: 4 - Beta
Classifier: Intended Audience :: Science/Research
Classifier: Topic :: Scientific/Engineering :: Artificial Intelligence
Classifier: Programming Language :: Python :: 3
Classifier: Programming Language :: Python :: 3.9
Classifier: Programming Language :: Python :: 3.10
Classifier: Programming Language :: Python :: 3.11
Classifier: Programming Language :: Python :: 3.12
Requires-Python: >=3.9
License-File: LICENSE
Requires-Dist: pandas>=2.0.0
Requires-Dist: numpy>=1.24.0
Provides-Extra: dev
Requires-Dist: pytest>=7.0.0; extra == "dev"
Requires-Dist: black>=23.0.0; extra == "dev"
Requires-Dist: flake8>=6.0.0; extra == "dev"
Dynamic: license-file
